[
  {
    "certificateNumber": "242093481603927",
    "certificateType": "1",
    "fatherName": "SAIDUL ISLAM MONDAL",
    "itiAddress": "DHALDANGA, BANKURA BANKURA, WEST BENGAL 722101",
    "trainingDuration": "Aug 2023 to July 2024",
    "certified": true,
    "certificateIssueDate": "07-Sep-2024",
    "rollNumber": "R230930807635",
    "examSystem": "A",
    "traineeName": "NABIR GOLAM MONDAL",
    "academicSession": "Aug 2023",
    "tradeName": "Welder",
    "examSession": "July 2024",
    "itiCode": "PR19000171",
    "itiName": "BANKURA PRIVATE ITI",
    "overallResult": "Pass",
    "resultDate": "07-Sep-2024",
    "marks": [
      {
        "year": "Year-1",
        "examSession": "July 2024",
        "resultDate": "07-Sep-2024",
        "tradeTheoryMax": 100,
        "tradeTheorySecured": 85,
        "employabilitySkillsMax": 50,
        "employabilitySkillsSecured": 47,
        "workshopCalculationMax": 50,
        "workshopCalculationSecured": 35,
        "engineeringDrawingMax": 50,
        "engineeringDrawingSecured": 38,
        "tradePracticalMax": 250,
        "tradePracticalSecured": 226,
        "formativeAssessmentMax": 200,
        "formativeAssessmentSecured": 165,
        "totalMax": 700,
        "totalSecured": 596
      }
    ]
  },
  {
    "rollNumber": "R160819039817",
    "certificateNumber": "181940068209759",
    "traineeName": "MANIK JANA",
    "fatherName": "SANTOSH KUMAR JANA",
    "motherName": "ARATI RANI JANA",
    "dateOfBirth": "05-Mar-1998",
    "itiName": "MECHEDA VIDYASAGAR PRIVATE ITI",
    "itiCode": "PR19000189",
    "itiAddress": "Dupjora, Mecheda, Kolaghat",
    "district": "MEDINIPUR EAST",
    "state": "WEST BENGAL",
    "pinCode": "721137",
    "academicSession": "Aug 2016",
    "year": "All",
    "examSystem": "A",
    "examSession": "Jul 2018",
    "resultDate": "29-Aug-2018",
    "tradeName": "Fitter",
    "trainingDuration": "Aug 2016 To Jul 2018",
    "level": "5",
    "certificateType": "1",
    "certificateIssueDate": "29-Aug-2018",
    "certified": true,
    "overallResult": "Pass",
    "disable": null,
    "marks": [
      {
        "year": "Year-1",
        "examSession": "Jul 2017",
        "resultDate": "07-Aug-2017",
        "tradeTheoryMax": 100,
        "tradeTheorySecured": 61,
        "employabilitySkillsMax": 50,
        "employabilitySkillsSecured": 33,
        "workshopCalculationMax": 50,
        "workshopCalculationSecured": 41,
        "engineeringDrawingMax": 50,
        "engineeringDrawingSecured": 32,
        "tradePracticalMax": 250,
        "tradePracticalSecured": 168,
        "formativeAssessmentMax": 200,
        "formativeAssessmentSecured": 158,
        "totalMax": 700,
        "totalSecured": 493
      },
      {
        "year": "Year-2",
        "examSession": "Jul 2018",
        "resultDate": "29-Aug-2018",
        "tradeTheoryMax": 100,
        "tradeTheorySecured": 81,
        "employabilitySkillsMax": 0,
        "employabilitySkillsSecured": 0,
        "workshopCalculationMax": 50,
        "workshopCalculationSecured": 47,
        "engineeringDrawingMax": 50,
        "engineeringDrawingSecured": 37,
        "tradePracticalMax": 250,
        "tradePracticalSecured": 204,
        "formativeAssessmentMax": 250,
        "formativeAssessmentSecured": 194,
        "totalMax": 650,
        "totalSecured": 563
      }
    ],
    "submissionDate": "2025-09-07T10:30:53.317Z"
  },
  {
    "rollNumber": "R210809230709",
    "certificateNumber": "230990251004315",
    "traineeName": "ANJARUL HOQUE",
    "fatherName": "ATIKUL SK",
    "motherName": "MORJINA BIBI",
    "dateOfBirth": "21-Feb-2005",
    "itiName": "GOVERNMENT ITI SAGARDIGHI",
    "itiCode": "GR19000167",
    "itiAddress": "POPARA,VILL & P.O-SA",
    "district": "MURSHIDABAD",
    "state": "WEST BENGAL",
    "pinCode": "742226",
    "academicSession": "Aug 2021",
    "year": "All",
    "examSystem": "A",
    "examSession": "Jul 2023",
    "resultDate": "07-Aug-2023",
    "tradeName": "Fitter",
    "trainingDuration": "Aug 2021 to Jul 2023",
    "level": "5",
    "certificateType": "1",
    "certificateIssueDate": "07-Aug-2023",
    "certified": true,
    "overallResult": "Pass",
    "disable": null,
    "submissionDate": "2025-09-15T13:36:18.675Z",
    "marks": [
      {
        "year": "Year-1",
        "examSession": "Jul 2022",
        "resultDate": "19-Aug-2022",
        "tradeTheoryMax": 100,
        "tradeTheorySecured": 74,
        "employabilitySkillsMax": 50,
        "employabilitySkillsSecured": 44,
        "workshopCalculationMax": 50,
        "workshopCalculationSecured": 34,
        "engineeringDrawingMax": 50,
        "engineeringDrawingSecured": 42,
        "tradePracticalMax": 250,
        "tradePracticalSecured": 197,
        "formativeAssessmentMax": 200,
        "formativeAssessmentSecured": 148,
        "totalMax": 700,
        "totalSecured": 539
      },
      {
        "year": "Year-2",
        "examSession": "Jul 2023",
        "resultDate": "07-Aug-2023",
        "tradeTheoryMax": 100,
        "tradeTheorySecured": 58,
        "employabilitySkillsMax": 0,
        "employabilitySkillsSecured": 0,
        "workshopCalculationMax": 50,
        "workshopCalculationSecured": 35,
        "engineeringDrawingMax": 50,
        "engineeringDrawingSecured": 38,
        "tradePracticalMax": 250,
        "tradePracticalSecured": 205,
        "formativeAssessmentMax": 250,
        "formativeAssessmentSecured": 196,
        "totalMax": 650,
        "totalSecured": 532
      }
    ]
  },
  {
    "rollNumber": "R2309308577556",
    "certificateNumber": "45754685466",
    "traineeName": "FYYY",
    "fatherName": "GHJHH",
    "motherName": "TGH6TY",
    "dateOfBirth": "10-Sep-2008",
    "itiName": "MECHEDA VIDYASAGAR PRIVATE ITI",
    "itiCode": "PR19000171",
    "itiAddress": "Dupjora, Mecheda, Kolaghat",
    "district": "MEDINIPUR EAST",
    "state": "WEST BENGAL",
    "pinCode": "721137",
    "academicSession": "Sep 2025",
    "year": "All",
    "examSystem": "A",
    "examSession": "Sep 2025",
    "resultDate": "24-Sep-2025",
    "tradeName": "Fitter",
    "trainingDuration": "Sep 2025",
    "level": "5",
    "certificateType": "1",
    "certificateIssueDate": "24-Sep-2025",
    "certified": true,
    "overallResult": "Pass",
    "disable": "https://ncvtmis.gov.in",
    "submissionDate": "2025-09-23T19:11:19.671Z",
    "formData": {
      "admissionDate": "7445",
      "uidNo": "Y34y44tyy",
      "gender": "Male",
      "category": "SC",
      "minority": "Hindu",
      "stateRegNo": "R5yfryuyty",
      "mobileNo": "9288258628552",
      "emailId": "456rgg@mail.to",
      "highestQualification": "10th",
      "isDualMode": "Yes",
      "applicationFormNo": "5856765",
      "traineeType": "Regular",
      "shift": "Shift 1",
      "unit": "Unit 1",
      "remarks": "Rtgdf gyrt ",
      "attendanceQ1": "85",
      "attendanceQ2": "85",
      "examFee": "Yes",
      "q1SessionalMarks": "Yes",
      "q2SessionalMarks": "Yes",
      "eligibilityStatus": "Yes"
    },
    "marks": [
      {
        "year": "Year-1",
        "examSession": "Sep 2025",
        "resultDate": "24-Sep-2025",
        "tradeTheoryMax": 100,
        "tradeTheorySecured": 63,
        "employabilitySkillsMax": 50,
        "employabilitySkillsSecured": 45,
        "workshopCalculationMax": 50,
        "workshopCalculationSecured": 45,
        "engineeringDrawingMax": 50,
        "engineeringDrawingSecured": 45,
        "tradePracticalMax": 250,
        "tradePracticalSecured": 145,
        "formativeAssessmentMax": 200,
        "formativeAssessmentSecured": 145,
        "totalMax": 700,
        "totalSecured": 488
      },
      {
        "year": "Year-2",
        "examSession": "Sep 2025",
        "resultDate": "03-Sep-2025",
        "tradeTheoryMax": 100,
        "tradeTheorySecured": 85,
        "employabilitySkillsMax": 0,
        "employabilitySkillsSecured": 0,
        "workshopCalculationMax": 50,
        "workshopCalculationSecured": 48,
        "engineeringDrawingMax": 50,
        "engineeringDrawingSecured": 45,
        "tradePracticalMax": 250,
        "tradePracticalSecured": 178,
        "formativeAssessmentMax": 250,
        "formativeAssessmentSecured": 169,
        "totalMax": 650,
        "totalSecured": 525
      }
    ]
  },
  {
    "rollNumber": "90807789",
    "certificateNumber": "07678686778",
    "traineeName": "YYU IYUUTU UUU",
    "fatherName": "YIYYUIN UI9UU",
    "motherName": "HIUUIU UIIUU",
    "dateOfBirth": "24-Sep-2025",
    "admissionDate": "767",
    "photoUrl": "https://raw.githubusercontent.com/Horsamod/itidata/main/assets/90807789_YYU_IYUUTU_UUU.jpg",
    "uidNo": "778988688",
    "gender": "Male",
    "category": "SC",
    "minority": "Hindu",
    "stateRegNo": "Ydfifci",
    "mobileNo": "6886868686",
    "emailId": "jcfifigogf9t@gmail.com",
    "highestQualification": "12th",
    "traineeDualMode": "Yes",
    "applicationFormNo": "Ifgooffiglg",
    "traineeType": "Regular",
    "shift": "Shift 1",
    "unit": "Unit 1",
    "remarks": "",
    "attendanceQ1": 56,
    "attendanceQ2": 96,
    "examFee": "Yes",
    "q1SessionalMarks": "Yes",
    "q2SessionalMarks": "Yes",
    "eligibilityStatus": "Yes",
    "theoryHallTicketUrl": null,
    "markSheetYear1Url": null,
    "markSheetYear2Url": null,
    "hallTicketUrl": null,
    "itiName": "BANKURA PRIVATE ITI",
    "itiCode": "PR19000171",
    "itiAddress": "DHALDANGA, BANKURA BANKURA, WEST BENGAL 722101",
    "district": "MEDINIPUR EAST",
    "state": "WEST BENGAL",
    "pinCode": "721137",
    "academicSession": "Sep 2025",
    "year": "Year-1",
    "examSystem": "A",
    "examSession": "Sep 2025",
    "resultDate": "24-Sep-2025",
    "tradeName": "Welder",
    "trainingDuration": "Sep 2025 To Sep 2025",
    "level": "5",
    "certificateType": "1",
    "certificateIssueDate": "24-Sep-2025",
    "certified": true,
    "overallResult": "Pass",
    "disable": "https://ncvtmis.gov.in",
    "submissionDate": "2025-09-24T02:41:33.251Z",
    "marks": [
      {
        "year": "Year-1",
        "examSession": "Sep 2025",
        "resultDate": "24-Sep-2025",
        "tradeTheoryMax": 100,
        "tradeTheorySecured": 85,
        "employabilitySkillsMax": 50,
        "employabilitySkillsSecured": 45,
        "workshopCalculationMax": 50,
        "workshopCalculationSecured": 45,
        "engineeringDrawingMax": 50,
        "engineeringDrawingSecured": 45,
        "tradePracticalMax": 250,
        "tradePracticalSecured": 148,
        "formativeAssessmentMax": 200,
        "formativeAssessmentSecured": 142,
        "totalMax": 700,
        "totalSecured": 510
      }
    ]
  },
  {
    "rollNumber": "R2108092306888",
    "certificateNumber": "230990681004758",
    "traineeName": "JALIMUL HAQUE SARDAR",
    "fatherName": "MOHAMMAD SAHAN SARDAR",
    "motherName": "MORTUBA SARDAR",
    "dateOfBirth": "26-Sep-2025",
    "admissionDate": "26-Sep-2025",
    "photoUrl": null,
    "uidNo": "966788997898",
    "gender": "Male",
    "category": "OBC",
    "minority": "Muslim",
    "stateRegNo": "9788877",
    "mobileNo": "3553868609",
    "emailId": "jcfifigogf9t@gmail.com",
    "highestQualification": "10th",
    "traineeDualMode": "Yes",
    "applicationFormNo": "Ifgooffiglg",
    "traineeType": "Regular",
    "shift": "Shift 1",
    "unit": "Unit 1",
    "remarks": "Test remark and not",
    "marksheetAllUrl": null,
    "certificateUrl": null,
    "markSheetYear1Url": null,
    "markSheetYear2Url": null,
    "itiName": "BANKURA PRIVATE ITI",
    "itiCode": "PR19000171",
    "itiAddress": "DHALDANGA, BANKURA BANKURA, WEST BENGAL 722101",
    "district": "MEDINIPUR EAST",
    "state": "WEST BENGAL",
    "pinCode": "721137",
    "academicSession": "Sep 2025",
    "year": "All",
    "examSystem": "Annual",
    "examSession": "Sep 2025",
    "resultDate": "26-Sep-2025",
    "tradeName": "Electrician",
    "trainingDuration": "Sep 2025 To Sep 2025",
    "level": "Level-5",
    "certificateType": "1",
    "certificateIssueDate": "26-Sep-2025",
    "certified": true,
    "disable": null,
    "submissionDate": "2025-09-26T07:09:58.412Z",
    "marks": [
      {
        "year": "Year-1",
        "examSession": "Sep 2025",
        "resultDate": "26-Sep-2025",
        "tradeTheoryMax": 100,
        "tradeTheorySecured": 85,
        "employabilitySkillsMax": 50,
        "employabilitySkillsSecured": 45,
        "workshopCalculationMax": 50,
        "workshopCalculationSecured": 45,
        "engineeringDrawingMax": 50,
        "engineeringDrawingSecured": 45,
        "tradePracticalMax": 250,
        "tradePracticalSecured": 185,
        "formativeAssessmentMax": 200,
        "formativeAssessmentSecured": 147,
        "totalMax": 700,
        "totalSecured": 552
      },
      {
        "year": "Year-2",
        "examSession": "Sep 2025",
        "resultDate": "26-Sep-2025",
        "tradeTheoryMax": 100,
        "tradeTheorySecured": 85,
        "employabilitySkillsMax": 50,
        "employabilitySkillsSecured": 45,
        "workshopCalculationMax": 50,
        "workshopCalculationSecured": 45,
        "engineeringDrawingMax": 50,
        "engineeringDrawingSecured": 45,
        "tradePracticalMax": 250,
        "tradePracticalSecured": 185,
        "formativeAssessmentMax": 200,
        "formativeAssessmentSecured": 145,
        "totalMax": 700,
        "totalSecured": 550
      }
    ]
  },
  {
    "rollNumber": "R1795578579685",
    "certificateNumber": "199559569666959",
    "traineeName": "APURBO BANNERJE",
    "fatherName": "ANIK BANNERJE",
    "motherName": "RUPOMA BANNERJER",
    "dateOfBirth": "26-Sep-2025",
    "admissionDate": "26-Sep-2025",
    "photoUrl": "https://raw.githubusercontent.com/Horsamod/itidata/main/assets/photoid/R1795578579685_APURBO_BANNERJE.jpg",
    "uidNo": "858595959595",
    "gender": "Male",
    "category": "General",
    "minority": "Hindu",
    "stateRegNo": "85544849595",
    "mobileNo": "9868686868",
    "emailId": "jcfifigogf9t@gmail.com",
    "highestQualification": "12th",
    "traineeDualMode": "Yes",
    "applicationFormNo": "848484848484",
    "traineeType": "Regular",
    "shift": "Shift 1",
    "unit": "Unit 1",
    "remarks": "Test remark and not",
    "marksheetAllUrl": "https://raw.githubusercontent.com/Horsamod/itidata/main/assets/files/R1795578579685_MarksheetAll.pdf",
    "certificateUrl": "https://raw.githubusercontent.com/Horsamod/itidata/main/assets/files/R1795578579685_Certificate.pdf",
    "markSheetYear1Url": "https://raw.githubusercontent.com/Horsamod/itidata/main/assets/files/R1795578579685_MarkSheetYear1.pdf",
    "markSheetYear2Url": "https://raw.githubusercontent.com/Horsamod/itidata/main/assets/files/R1795578579685_MarkSheetYear2.pdf",
    "itiName": "GOVERNMENT ITI SAGARDIGHI",
    "itiCode": "GR19000167",
    "itiAddress": "Dupjora, Mecheda, Kolaghat",
    "district": "MURSHIDABAD",
    "state": "WEST BENGAL",
    "pinCode": "742226",
    "academicSession": "Sep 2025",
    "year": "All",
    "examSystem": "A",
    "examSession": "Sep 2025",
    "resultDate": "26-Sep-2025",
    "tradeName": "Electrician",
    "trainingDuration": "Sep 2025 To Sep 2025",
    "level": "5",
    "certificateType": "1",
    "certificateIssueDate": "26-Sep-2025",
    "certified": true,
    "disable": null,
    "submissionDate": "2025-09-26T11:09:29.572Z",
    "marks": [
      {
        "year": "Year-1",
        "examSession": "Sep 2025",
        "resultDate": "26-Sep-2025",
        "tradeTheoryMax": 100,
        "tradeTheorySecured": 75,
        "employabilitySkillsMax": 50,
        "employabilitySkillsSecured": 40,
        "workshopCalculationMax": 50,
        "workshopCalculationSecured": 45,
        "engineeringDrawingMax": 50,
        "engineeringDrawingSecured": 42,
        "tradePracticalMax": 250,
        "tradePracticalSecured": 196,
        "formativeAssessmentMax": 200,
        "formativeAssessmentSecured": 175,
        "totalMax": 700,
        "totalSecured": 573
      },
      {
        "year": "Year-2",
        "examSession": "Sep 2025",
        "resultDate": "26-Sep-2025",
        "tradeTheoryMax": 100,
        "tradeTheorySecured": 78,
        "employabilitySkillsMax": 0,
        "employabilitySkillsSecured": 0,
        "workshopCalculationMax": 50,
        "workshopCalculationSecured": 47,
        "engineeringDrawingMax": 50,
        "engineeringDrawingSecured": 48,
        "tradePracticalMax": 250,
        "tradePracticalSecured": 182,
        "formativeAssessmentMax": 250,
        "formativeAssessmentSecured": 148,
        "totalMax": 650,
        "totalSecured": 503
      }
    ]
  },
  {
    "rollNumber": "R2096689998667",
    "certificateNumber": "229805578764576",
    "traineeName": "RAHIM MANDAL",
    "fatherName": "RAMJAN MANDAL",
    "motherName": "RESMA BIBI",
    "dateOfBirth": "26-Sep-2015",
    "admissionDate": "26-Sep-2025",
    "photoUrl": null,
    "uidNo": "589598449494",
    "gender": "Male",
    "category": "OBC",
    "minority": "Muslim",
    "stateRegNo": "5858558595",
    "mobileNo": "7676467676",
    "emailId": "jcfifigogf9t@gmail.com",
    "highestQualification": "10th",
    "traineeDualMode": "Yes",
    "applicationFormNo": "85858489",
    "traineeType": "Regular",
    "shift": "Shift 1",
    "unit": "Unit 1",
    "remarks": "Test remark and not",
    "marksheetAllUrl": null,
    "certificateUrl": null,
    "markSheetYear1Url": null,
    "markSheetYear2Url": null,
    "itiName": "GOVERNMENT ITI SAGARDIGHI",
    "itiCode": "PR19000171",
    "itiAddress": "DHALDANGA, BANKURA BANKURA, WEST BENGAL 722101",
    "district": "MEDINIPUR EAST",
    "state": "WEST BENGAL",
    "pinCode": "742226",
    "academicSession": "Sep 2025",
    "year": "All",
    "examSystem": "A",
    "examSession": "Sep 2025",
    "resultDate": "26-Sep-2025",
    "tradeName": "Electrician",
    "trainingDuration": "Sep 2025 To Sep 2025",
    "level": "5",
    "certificateType": "1",
    "certificateIssueDate": "26-Sep-2025",
    "certified": true,
    "disable": null,
    "submissionDate": "2025-09-26T11:48:13.782Z",
    "marks": [
      {
        "year": "Year-1",
        "examSession": "Sep 2025",
        "resultDate": "26-Sep-2025",
        "tradeTheoryMax": 100,
        "tradeTheorySecured": 86,
        "employabilitySkillsMax": 50,
        "employabilitySkillsSecured": 48,
        "workshopCalculationMax": 50,
        "workshopCalculationSecured": 40,
        "engineeringDrawingMax": 50,
        "engineeringDrawingSecured": 38,
        "tradePracticalMax": 250,
        "tradePracticalSecured": 202,
        "formativeAssessmentMax": 200,
        "formativeAssessmentSecured": 180,
        "totalMax": 700,
        "totalSecured": 594
      },
      {
        "year": "Year-2",
        "examSession": "Sep 2025",
        "resultDate": "26-Sep-2025",
        "tradeTheoryMax": 100,
        "tradeTheorySecured": 78,
        "employabilitySkillsMax": 0,
        "employabilitySkillsSecured": 0,
        "workshopCalculationMax": 50,
        "workshopCalculationSecured": 45,
        "engineeringDrawingMax": 50,
        "engineeringDrawingSecured": 40,
        "tradePracticalMax": 250,
        "tradePracticalSecured": 185,
        "formativeAssessmentMax": 250,
        "formativeAssessmentSecured": 152,
        "totalMax": 650,
        "totalSecured": 500
      }
    ]
  },
  {
    "rollNumber": "R160819019935",
    "certificateNumber": "180967000075075",
    "traineeName": "AMDADUL HAQUE SARDAR",
    "fatherName": "MOHAMMAD SAHAN SARDAR",
    "motherName": "MORTUBA SARDAR",
    "dateOfBirth": "01-Feb-1999",
    "admissionDate": "28-Jul-2016",
    "photoUrl": "https://raw.githubusercontent.com/Horsamod/itidata/main/assets/photoid/R160819019935_AMDADUL_HAQUE_SARDAR.jpg",
    "uidNo": "369852347895",
    "gender": "Male",
    "category": "OBC",
    "minority": "Muslim",
    "stateRegNo": "529074",
    "mobileNo": "7896541230",
    "emailId": "jcfifigogf9t@gmail.com",
    "highestQualification": "10th",
    "traineeDualMode": "Yes",
    "applicationFormNo": "7578678",
    "traineeType": "Regular",
    "shift": "Shift 1",
    "unit": "Unit 1",
    "remarks": "Test remark and not",
    "marksheetAllUrl": "https://raw.githubusercontent.com/Horsamod/itidata/main/assets/files/R160819019935/R160819019935_Marksheet_All.css",
    "certificateUrl": "https://raw.githubusercontent.com/Horsamod/itidata/main/assets/files/R160819019935/R160819019935_NCVTCertificate.pdf",
    "markSheetYear1Url": "https://raw.githubusercontent.com/Horsamod/itidata/main/assets/files/R160819019935/R160819019935_MarkSheet_Year_1.pdf",
    "markSheetYear2Url": "https://raw.githubusercontent.com/Horsamod/itidata/main/assets/files/R160819019935/R160819019935_MarkSheet_Year_2.pdf",
    "itiName": "BANKURA PRIVATE ITI",
    "itiCode": "PR19000171",
    "itiAddress": "DHALDANGA, BANKURA BANKURA, WEST BENGAL 722101",
    "district": "MEDINIPUR EAST",
    "state": "WEST BENGAL",
    "pinCode": "721137",
    "academicSession": "Jul 2016",
    "year": "All",
    "examSystem": "A",
    "examSession": "Jul 2018",
    "resultDate": "29-Aug-2018",
    "tradeName": "Electrician",
    "trainingDuration": "Jul 2016 To Aug 2018",
    "level": "5",
    "certificateType": "1",
    "certificateIssueDate": "29-Aug-2018",
    "certified": true,
    "disable": null,
    "submissionDate": "2025-09-24T12:23:32.613Z",
    "marks": [
      {
        "year": "Year-1",
        "examSession": "Jul 2017",
        "resultDate": "07-Aug-2017",
        "tradeTheoryMax": 100,
        "tradeTheorySecured": 84,
        "employabilitySkillsMax": 50,
        "employabilitySkillsSecured": 42,
        "workshopCalculationMax": 50,
        "workshopCalculationSecured": 46,
        "engineeringDrawingMax": 50,
        "engineeringDrawingSecured": 45,
        "tradePracticalMax": 250,
        "tradePracticalSecured": 208,
        "formativeAssessmentMax": 200,
        "formativeAssessmentSecured": 175,
        "totalMax": 700,
        "totalSecured": 600
      },
      {
        "year": "Year-2",
        "examSession": "Jul 2018",
        "resultDate": "29-Aug-2018",
        "tradeTheoryMax": 100,
        "tradeTheorySecured": 78,
        "employabilitySkillsMax": 0,
        "employabilitySkillsSecured": 0,
        "workshopCalculationMax": 50,
        "workshopCalculationSecured": 44,
        "engineeringDrawingMax": 50,
        "engineeringDrawingSecured": 40,
        "tradePracticalMax": 250,
        "tradePracticalSecured": 190,
        "formativeAssessmentMax": 250,
        "formativeAssessmentSecured": 185,
        "totalMax": 650,
        "totalSecured": 537
      }
    ]
  },
  {
    "rollNumber": "R170720021456",
    "certificateNumber": "190765000123456",
    "traineeName": "SANTOSH KUMAR YADAV",
    "fatherName": "RAM PRASAD YADAV",
    "motherName": "KAMLA DEVI",
    "dateOfBirth": "12-Apr-1998",
    "admissionDate": "15-Jul-2017",
    "photoUrl": "https://raw.githubusercontent.com/Horsamod/itidata/main/assets/photoid/R170720021456_SANTOSH_KUMAR_YADAV.jpg",
    "uidNo": "583920174628",
    "gender": "Male",
    "category": "OBC",
    "minority": "None",
    "stateRegNo": "612345",
    "mobileNo": "8765432109",
    "emailId": "santosh.yadav98@gmail.com",
    "highestQualification": "10th",
    "traineeDualMode": "Yes",
    "applicationFormNo": "9876543",
    "traineeType": "Regular",
    "shift": "Shift 1",
    "unit": "Unit 2",
    "remarks": "Completed training successfully",
    "marksheetAllUrl": "https://raw.githubusercontent.com/Horsamod/itidata/main/assets/files/R170720021456/R170720021456_Marksheet_All.css",
    "certificateUrl": "https://raw.githubusercontent.com/Horsamod/itidata/main/assets/files/R170720021456/R170720021456_NCVTCertificate.pdf",
    "markSheetYear1Url": "https://raw.githubusercontent.com/Horsamod/itidata/main/assets/files/R170720021456/R170720021456_MarkSheet_Year_1.pdf",
    "markSheetYear2Url": "https://raw.githubusercontent.com/Horsamod/itidata/main/assets/files/R170720021456/R170720021456_MarkSheet_Year_2.pdf",
    "itiName": "PURULIA PRIVATE ITI",
    "itiCode": "PR19000189",
    "itiAddress": "RANCHI ROAD, PURULIA, WEST BENGAL 723101",
    "district": "PURULIA",
    "state": "WEST BENGAL",
    "pinCode": "723101",
    "academicSession": "Jul 2017",
    "year": "All",
    "examSystem": "A",
    "examSession": "Jul 2019",
    "resultDate": "25-Aug-2019",
    "tradeName": "Mechanic Diesel",
    "trainingDuration": "Jul 2017 To Aug 2019",
    "level": "5",
    "certificateType": "1",
    "certificateIssueDate": "25-Aug-2019",
    "certified": true,
    "disable": null,
    "submissionDate": "2025-09-26T10:15:22.456Z",
    "marks": [
      {
        "year": "Year-1",
        "examSession": "Jul 2018",
        "resultDate": "10-Aug-2018",
        "tradeTheoryMax": 100,
        "tradeTheorySecured": 85,
        "employabilitySkillsMax": 50,
        "employabilitySkillsSecured": 40,
        "workshopCalculationMax": 50,
        "workshopCalculationSecured": 43,
        "engineeringDrawingMax": 50,
        "engineeringDrawingSecured": 46,
        "tradePracticalMax": 250,
        "tradePracticalSecured": 210,
        "formativeAssessmentMax": 200,
        "formativeAssessmentSecured": 170,
        "totalMax": 700,
        "totalSecured": 594
      },
      {
        "year": "Year-2",
        "examSession": "Jul 2019",
        "resultDate": "25-Aug-2019",
        "tradeTheoryMax": 100,
        "tradeTheorySecured": 80,
        "employabilitySkillsMax": 0,
        "employabilitySkillsSecured": 0,
        "workshopCalculationMax": 50,
        "workshopCalculationSecured": 45,
        "engineeringDrawingMax": 50,
        "engineeringDrawingSecured": 42,
        "tradePracticalMax": 250,
        "tradePracticalSecured": 195,
        "formativeAssessmentMax": 250,
        "formativeAssessmentSecured": 180,
        "totalMax": 650,
        "totalSecured": 542
      }
    ]
  },
  {
    "rollNumber": "R180820022789",
    "certificateNumber": "200987000456789",
    "traineeName": "PRIYA MONDAL",
    "fatherName": "SUBRATA MONDAL",
    "motherName": "ANJALI MONDAL",
    "dateOfBirth": "25-Jun-2000",
    "admissionDate": "20-Aug-2018",
    "photoUrl": "https://raw.githubusercontent.com/Horsamod/itidata/main/assets/photoid/R180820022789_PRIYA_MONDAL.jpg",
    "uidNo": "719283506431",
    "gender": "Female",
    "category": "SC",
    "minority": "None",
    "stateRegNo": "745632",
    "mobileNo": "9123456789",
    "emailId": "priya.mondal2k@gmail.com",
    "highestQualification": "12th",
    "traineeDualMode": "No",
    "applicationFormNo": "8765432",
    "traineeType": "Regular",
    "shift": "Shift 2",
    "unit": "Unit 1",
    "remarks": "Good performance in practicals",
    "marksheetAllUrl": "https://raw.githubusercontent.com/Horsamod/itidata/main/assets/files/R180820022789/R180820022789_Marksheet_All.css",
    "certificateUrl": "https://raw.githubusercontent.com/Horsamod/itidata/main/assets/files/R180820022789/R180820022789_NCVTCertificate.pdf",
    "markSheetYear1Url": "https://raw.githubusercontent.com/Horsamod/itidata/main/assets/files/R180820022789/R180820022789_MarkSheet_Year_1.pdf",
    "markSheetYear2Url": "https://raw.githubusercontent.com/Horsamod/itidata/main/assets/files/R180820022789/R180820022789_MarkSheet_Year_2.pdf",
    "itiName": "HOWRAH TECHNICAL ITI",
    "itiCode": "PR19000212",
    "itiAddress": "SHIBPUR, HOWRAH, WEST BENGAL 711102",
    "district": "HOWRAH",
    "state": "WEST BENGAL",
    "pinCode": "711102",
    "academicSession": "Aug 2018",
    "year": "All",
    "examSystem": "A",
    "examSession": "Jul 2020",
    "resultDate": "30-Aug-2020",
    "tradeName": "Electronics Mechanic",
    "trainingDuration": "Aug 2018 To Aug 2020",
    "level": "5",
    "certificateType": "1",
    "certificateIssueDate": "30-Aug-2020",
    "certified": true,
    "disable": null,
    "submissionDate": "2025-09-26T11:30:45.789Z",
    "marks": [
      {
        "year": "Year-1",
        "examSession": "Jul 2019",
        "resultDate": "15-Aug-2019",
        "tradeTheoryMax": 100,
        "tradeTheorySecured": 90,
        "employabilitySkillsMax": 50,
        "employabilitySkillsSecured": 48,
        "workshopCalculationMax": 50,
        "workshopCalculationSecured": 45,
        "engineeringDrawingMax": 50,
        "engineeringDrawingSecured": 47,
        "tradePracticalMax": 250,
        "tradePracticalSecured": 220,
        "formativeAssessmentMax": 200,
        "formativeAssessmentSecured": 185,
        "totalMax": 700,
        "totalSecured": 635
      },
      {
        "year": "Year-2",
        "examSession": "Jul 2020",
        "resultDate": "30-Aug-2020",
        "tradeTheoryMax": 100,
        "tradeTheorySecured": 85,
        "employabilitySkillsMax": 0,
        "employabilitySkillsSecured": 0,
        "workshopCalculationMax": 50,
        "workshopCalculationSecured": 48,
        "engineeringDrawingMax": 50,
        "engineeringDrawingSecured": 46,
        "tradePracticalMax": 250,
        "tradePracticalSecured": 205,
        "formativeAssessmentMax": 250,
        "formativeAssessmentSecured": 195,
        "totalMax": 650,
        "totalSecured": 579
      }
    ]
  },
  {
    "rollNumber": "R160620019876",
    "certificateNumber": "180543000987654",
    "traineeName": "MD ASIF IQBAL",
    "fatherName": "MD RAFIQUE IQBAL",
    "motherName": "SALMA KHATOON",
    "dateOfBirth": "03-Sep-1997",
    "admissionDate": "25-Jun-2016",
    "photoUrl": "https://raw.githubusercontent.com/Horsamod/itidata/main/assets/photoid/R160620019876_MD_ASIF_IQBAL.jpg",
    "uidNo": "648291735120",
    "gender": "Male",
    "category": "OBC",
    "minority": "Muslim",
    "stateRegNo": "587654",
    "mobileNo": "8901234567",
    "emailId": "asif.iqbal97@gmail.com",
    "highestQualification": "10th",
    "traineeDualMode": "Yes",
    "applicationFormNo": "7654321",
    "traineeType": "Regular",
    "shift": "Shift 1",
    "unit": "Unit 3",
    "remarks": "Consistent performer",
    "marksheetAllUrl": "https://raw.githubusercontent.com/Horsamod/itidata/main/assets/files/R160620019876/R160620019876_Marksheet_All.css",
    "certificateUrl": "https://raw.githubusercontent.com/Horsamod/itidata/main/assets/files/R160620019876/R160620019876_NCVTCertificate.pdf",
    "markSheetYear1Url": "https://raw.githubusercontent.com/Horsamod/itidata/main/assets/files/R160620019876/R160620019876_MarkSheet_Year_1.pdf",
    "markSheetYear2Url": "https://raw.githubusercontent.com/Horsamod/itidata/main/assets/files/R160620019876/R160620019876_MarkSheet_Year_2.pdf",
    "itiName": "MALDA PRIVATE ITI",
    "itiCode": "PR19000145",
    "itiAddress": "ENGLISH BAZAR, MALDA, WEST BENGAL 732101",
    "district": "MALDA",
    "state": "WEST BENGAL",
    "pinCode": "732101",
    "academicSession": "Jul 2016",
    "year": "All",
    "examSystem": "A",
    "examSession": "Jul 2018",
    "resultDate": "28-Aug-2018",
    "tradeName": "Welder",
    "trainingDuration": "Jul 2016 To Aug 2018",
    "level": "5",
    "certificateType": "1",
    "certificateIssueDate": "28-Aug-2018",
    "certified": true,
    "disable": null,
    "submissionDate": "2025-09-25T09:12:34.567Z",
    "marks": [
      {
        "year": "Year-1",
        "examSession": "Jul 2017",
        "resultDate": "10-Aug-2017",
        "tradeTheoryMax": 100,
        "tradeTheorySecured": 82,
        "employabilitySkillsMax": 50,
        "employabilitySkillsSecured": 42,
        "workshopCalculationMax": 50,
        "workshopCalculationSecured": 40,
        "engineeringDrawingMax": 50,
        "engineeringDrawingSecured": 44,
        "tradePracticalMax": 250,
        "tradePracticalSecured": 200,
        "formativeAssessmentMax": 200,
        "formativeAssessmentSecured": 165,
        "totalMax": 700,
        "totalSecured": 573
      },
      {
        "year": "Year-2",
        "examSession": "Jul 2018",
        "resultDate": "28-Aug-2018",
        "tradeTheoryMax": 100,
        "tradeTheorySecured": 78,
        "employabilitySkillsMax": 0,
        "employabilitySkillsSecured": 0,
        "workshopCalculationMax": 50,
        "workshopCalculationSecured": 43,
        "engineeringDrawingMax": 50,
        "engineeringDrawingSecured": 41,
        "tradePracticalMax": 250,
        "tradePracticalSecured": 190,
        "formativeAssessmentMax": 250,
        "formativeAssessmentSecured": 175,
        "totalMax": 650,
        "totalSecured": 527
      }
    ]
  },
  {
    "rollNumber": "R190920023214",
    "certificateNumber": "210987000789123",
    "traineeName": "ANITA SINGH",
    "fatherName": "RAJESH SINGH",
    "motherName": "MEERA SINGH",
    "dateOfBirth": "17-Nov-1999",
    "admissionDate": "12-Sep-2019",
    "photoUrl": "https://raw.githubusercontent.com/Horsamod/itidata/main/assets/photoid/R190920023214_ANITA_SINGH.jpg",
    "uidNo": "392184750632",
    "gender": "Female",
    "category": "GENERAL",
    "minority": "None",
    "stateRegNo": "678901",
    "mobileNo": "7890123456",
    "emailId": "anita.singh99@gmail.com",
    "highestQualification": "12th",
    "traineeDualMode": "No",
    "applicationFormNo": "6543210",
    "traineeType": "Regular",
    "shift": "Shift 2",
    "unit": "Unit 2",
    "remarks": "Excellent in theory",
    "marksheetAllUrl": "https://raw.githubusercontent.com/Horsamod/itidata/main/assets/files/R190920023214/R190920023214_Marksheet_All.css",
    "certificateUrl": "https://raw.githubusercontent.com/Horsamod/itidata/main/assets/files/R190920023214/R190920023214_NCVTCertificate.pdf",
    "markSheetYear1Url": "https://raw.githubusercontent.com/Horsamod/itidata/main/assets/files/R190920023214/R190920023214_MarkSheet_Year_1.pdf",
    "markSheetYear2Url": "https://raw.githubusercontent.com/Horsamod/itidata/main/assets/files/R190920023214/R190920023214_MarkSheet_Year_2.pdf",
    "itiName": "BURDWAN TECHNICAL ITI",
    "itiCode": "PR19000278",
    "itiAddress": "KATWA ROAD, BURDWAN, WEST BENGAL 713101",
    "district": "BURDWAN",
    "state": "WEST BENGAL",
    "pinCode": "713101",
    "academicSession": "Sep 2019",
    "year": "All",
    "examSystem": "A",
    "examSession": "Jul 2021",
    "resultDate": "31-Aug-2021",
    "tradeName": "Computer Operator and Programming Assistant",
    "trainingDuration": "Sep 2019 To Aug 2021",
    "level": "5",
    "certificateType": "1",
    "certificateIssueDate": "31-Aug-2021",
    "certified": true,
    "disable": null,
    "submissionDate": "2025-09-26T13:22:11.234Z",
    "marks": [
      {
        "year": "Year-1",
        "examSession": "Jul 2020",
        "resultDate": "15-Aug-2020",
        "tradeTheoryMax": 100,
        "tradeTheorySecured": 92,
        "employabilitySkillsMax": 50,
        "employabilitySkillsSecured": 46,
        "workshopCalculationMax": 50,
        "workshopCalculationSecured": 48,
        "engineeringDrawingMax": 50,
        "engineeringDrawingSecured": 45,
        "tradePracticalMax": 250,
        "tradePracticalSecured": 225,
        "formativeAssessmentMax": 200,
        "formativeAssessmentSecured": 190,
        "totalMax": 700,
        "totalSecured": 646
      },
      {
        "year": "Year-2",
        "examSession": "Jul 2021",
        "resultDate": "31-Aug-2021",
        "tradeTheoryMax": 100,
        "tradeTheorySecured": 88,
        "employabilitySkillsMax": 0,
        "employabilitySkillsSecured": 0,
        "workshopCalculationMax": 50,
        "workshopCalculationSecured": 47,
        "engineeringDrawingMax": 50,
        "engineeringDrawingSecured": 44,
        "tradePracticalMax": 250,
        "tradePracticalSecured": 210,
        "formativeAssessmentMax": 250,
        "formativeAssessmentSecured": 200,
        "totalMax": 650,
        "totalSecured": 589
      }
    ]
  },
  {
    "rollNumber": "R180720022345",
    "certificateNumber": "200876000654321",
    "traineeName": "VIKASH PATEL",
    "fatherName": "SURESH PATEL",
    "motherName": "GEETA PATEL",
    "dateOfBirth": "08-Jan-2000",
    "admissionDate": "18-Jul-2018",
    "photoUrl": "https://raw.githubusercontent.com/Horsamod/itidata/main/assets/photoid/R180720022345_VIKASH_PATEL.jpg",
    "uidNo": "527381946013",
    "gender": "Male",
    "category": "OBC",
    "minority": "None",
    "stateRegNo": "598123",
    "mobileNo": "9012345678",
    "emailId": "vikash.patel2k@gmail.com",
    "highestQualification": "10th",
    "traineeDualMode": "Yes",
    "applicationFormNo": "5432109",
    "traineeType": "Regular",
    "shift": "Shift 1",
    "unit": "Unit 1",
    "remarks": "Strong practical skills",
    "marksheetAllUrl": "https://raw.githubusercontent.com/Horsamod/itidata/main/assets/files/R180720022345/R180720022345_Marksheet_All.css",
    "certificateUrl": "https://raw.githubusercontent.com/Horsamod/itidata/main/assets/files/R180720022345/R180720022345_NCVTCertificate.pdf",
    "markSheetYear1Url": "https://raw.githubusercontent.com/Horsamod/itidata/main/assets/files/R180720022345/R180720022345_MarkSheet_Year_1.pdf",
    "markSheetYear2Url": "https://raw.githubusercontent.com/Horsamod/itidata/main/assets/files/R180720022345/R180720022345_MarkSheet_Year_2.pdf",
    "itiName": "HOOGHLY PRIVATE ITI",
    "itiCode": "PR19000167",
    "itiAddress": "CHINSURAH, HOOGHLY, WEST BENGAL 712101",
    "district": "HOOGHLY",
    "state": "WEST BENGAL",
    "pinCode": "712101",
    "academicSession": "Jul 2018",
    "year": "All",
    "examSystem": "A",
    "examSession": "Jul 2020",
    "resultDate": "29-Aug-2020",
    "tradeName": "Turner",
    "trainingDuration": "Jul 2018 To Aug 2020",
    "level": "5",
    "certificateType": "1",
    "certificateIssueDate": "29-Aug-2020",
    "certified": true,
    "disable": null,
    "submissionDate": "2025-09-26T14:45:33.456Z",
    "marks": [
      {
        "year": "Year-1",
        "examSession": "Jul 2019",
        "resultDate": "10-Aug-2019",
        "tradeTheoryMax": 100,
        "tradeTheorySecured": 87,
        "employabilitySkillsMax": 50,
        "employabilitySkillsSecured": 44,
        "workshopCalculationMax": 50,
        "workshopCalculationSecured": 46,
        "engineeringDrawingMax": 50,
        "engineeringDrawingSecured": 43,
        "tradePracticalMax": 250,
        "tradePracticalSecured": 215,
        "formativeAssessmentMax": 200,
        "formativeAssessmentSecured": 180,
        "totalMax": 700,
        "totalSecured": 615
      },
      {
        "year": "Year-2",
        "examSession": "Jul 2020",
        "resultDate": "29-Aug-2020",
        "tradeTheoryMax": 100,
        "tradeTheorySecured": 83,
        "employabilitySkillsMax": 0,
        "employabilitySkillsSecured": 0,
        "workshopCalculationMax": 50,
        "workshopCalculationSecured": 45,
        "engineeringDrawingMax": 50,
        "engineeringDrawingSecured": 42,
        "tradePracticalMax": 250,
        "tradePracticalSecured": 200,
        "formativeAssessmentMax": 250,
        "formativeAssessmentSecured": 190,
        "totalMax": 650,
        "totalSecured": 560
      }
    ]
  },
  {
    "rollNumber": "R170820021987",
    "certificateNumber": "190876000321987",
    "traineeName": "RINA DAS",
    "fatherName": "NIRMAL DAS",
    "motherName": "SABITA DAS",
    "dateOfBirth": "22-May-1999",
    "admissionDate": "10-Aug-2017",
    "photoUrl": "https://raw.githubusercontent.com/Horsamod/itidata/main/assets/photoid/R170820021987_RINA_DAS.jpg",
    "uidNo": "681234597820",
    "gender": "Female",
    "category": "SC",
    "minority": "None",
    "stateRegNo": "654789",
    "mobileNo": "8123456780",
    "emailId": "rina.das99@gmail.com",
    "highestQualification": "12th",
    "traineeDualMode": "No",
    "applicationFormNo": "4321098",
    "traineeType": "Regular",
    "shift": "Shift 2",
    "unit": "Unit 3",
    "remarks": "Dedicated student",
    "marksheetAllUrl": "https://raw.githubusercontent.com/Horsamod/itidata/main/assets/files/R170820021987/R170820021987_Marksheet_All.css",
    "certificateUrl": "https://raw.githubusercontent.com/Horsamod/itidata/main/assets/files/R170820021987/R170820021987_NCVTCertificate.pdf",
    "markSheetYear1Url": "https://raw.githubusercontent.com/Horsamod/itidata/main/assets/files/R170820021987/R170820021987_MarkSheet_Year_1.pdf",
    "markSheetYear2Url": "https://raw.githubusercontent.com/Horsamod/itidata/main/assets/files/R170820021987/R170820021987_MarkSheet_Year_2.pdf",
    "itiName": "NADIA PRIVATE ITI",
    "itiCode": "PR19000123",
    "itiAddress": "KRISHNANAGAR, NADIA, WEST BENGAL 741101",
    "district": "NADIA",
    "state": "WEST BENGAL",
    "pinCode": "741101",
    "academicSession": "Aug 2017",
    "year": "All",
    "examSystem": "A",
    "examSession": "Jul 2019",
    "resultDate": "27-Aug-2019",
    "tradeName": "Draughtsman Civil",
    "trainingDuration": "Aug 2017 To Aug 2019",
    "level": "5",
    "certificateType": "1",
    "certificateIssueDate": "27-Aug-2019",
    "certified": true,
    "disable": null,
    "submissionDate": "2025-09-26T15:10:22.987Z",
    "marks": [
      {
        "year": "Year-1",
        "examSession": "Jul 2018",
        "resultDate": "12-Aug-2018",
        "tradeTheoryMax": 100,
        "tradeTheorySecured": 89,
        "employabilitySkillsMax": 50,
        "employabilitySkillsSecured": 45,
        "workshopCalculationMax": 50,
        "workshopCalculationSecured": 47,
        "engineeringDrawingMax": 50,
        "engineeringDrawingSecured": 46,
        "tradePracticalMax": 250,
        "tradePracticalSecured": 220,
        "formativeAssessmentMax": 200,
        "formativeAssessmentSecured": 185,
        "totalMax": 700,
        "totalSecured": 632
      },
      {
        "year": "Year-2",
        "examSession": "Jul 2019",
        "resultDate": "27-Aug-2019",
        "tradeTheoryMax": 100,
        "tradeTheorySecured": 86,
        "employabilitySkillsMax": 0,
        "employabilitySkillsSecured": 0,
        "workshopCalculationMax": 50,
        "workshopCalculationSecured": 46,
        "engineeringDrawingMax": 50,
        "engineeringDrawingSecured": 45,
        "tradePracticalMax": 250,
        "tradePracticalSecured": 205,
        "formativeAssessmentMax": 250,
        "formativeAssessmentSecured": 195,
        "totalMax": 650,
        "totalSecured": 577
      }
    ]
  },
  {
    "rollNumber": "R190820023456",
    "certificateNumber": "210987000123456",
    "traineeName": "ARJUN MAHATO",
    "fatherName": "GOPAL MAHATO",
    "motherName": "LAXMI MAHATO",
    "dateOfBirth": "30-Jul-2001",
    "admissionDate": "15-Aug-2019",
    "photoUrl": "https://raw.githubusercontent.com/Horsamod/itidata/main/assets/photoid/R190820023456_ARJUN_MAHATO.jpg",
    "uidNo": "456789123401",
    "gender": "Male",
    "category": "OBC",
    "minority": "None",
    "stateRegNo": "789123",
    "mobileNo": "7012345678",
    "emailId": "arjun.mahato01@gmail.com",
    "highestQualification": "10th",
    "traineeDualMode": "Yes",
    "applicationFormNo": "3210987",
    "traineeType": "Regular",
    "shift": "Shift 1",
    "unit": "Unit 2",
    "remarks": "Good practical knowledge",
    "marksheetAllUrl": "https://raw.githubusercontent.com/Horsamod/itidata/main/assets/files/R190820023456/R190820023456_Marksheet_All.css",
    "certificateUrl": "https://raw.githubusercontent.com/Horsamod/itidata/main/assets/files/R190820023456/R190820023456_NCVTCertificate.pdf",
    "markSheetYear1Url": "https://raw.githubusercontent.com/Horsamod/itidata/main/assets/files/R190820023456/R190820023456_MarkSheet_Year_1.pdf",
    "markSheetYear2Url": "https://raw.githubusercontent.com/Horsamod/itidata/main/assets/files/R190820023456/R190820023456_MarkSheet_Year_2.pdf",
    "itiName": "MURSHIDABAD PRIVATE ITI",
    "itiCode": "PR19000256",
    "itiAddress": "BERHAMPORE, MURSHIDABAD, WEST BENGAL 742101",
    "district": "MURSHIDABAD",
    "state": "WEST BENGAL",
    "pinCode": "742101",
    "academicSession": "Aug 2019",
    "year": "All",
    "examSystem": "A",
    "examSession": "Jul 2021",
    "resultDate": "30-Aug-2021",
    "tradeName": "Machinist",
    "trainingDuration": "Aug 2019 To Aug 2021",
    "level": "5",
    "certificateType": "1",
    "certificateIssueDate": "30-Aug-2021",
    "certified": true,
    "disable": null,
    "submissionDate": "2025-09-26T16:20:33.456Z",
    "marks": [
      {
        "year": "Year-1",
        "examSession": "Jul 2020",
        "resultDate": "15-Aug-2020",
        "tradeTheoryMax": 100,
        "tradeTheorySecured": 84,
        "employabilitySkillsMax": 50,
        "employabilitySkillsSecured": 42,
        "workshopCalculationMax": 50,
        "workshopCalculationSecured": 45,
        "engineeringDrawingMax": 50,
        "engineeringDrawingSecured": 43,
        "tradePracticalMax": 250,
        "tradePracticalSecured": 210,
        "formativeAssessmentMax": 200,
        "formativeAssessmentSecured": 175,
        "totalMax": 700,
        "totalSecured": 599
      },
      {
        "year": "Year-2",
        "examSession": "Jul 2021",
        "resultDate": "30-Aug-2021",
        "tradeTheoryMax": 100,
        "tradeTheorySecured": 80,
        "employabilitySkillsMax": 0,
        "employabilitySkillsSecured": 0,
        "workshopCalculationMax": 50,
        "workshopCalculationSecured": 44,
        "engineeringDrawingMax": 50,
        "engineeringDrawingSecured": 42,
        "tradePracticalMax": 250,
        "tradePracticalSecured": 195,
        "formativeAssessmentMax": 250,
        "formativeAssessmentSecured": 185,
        "totalMax": 650,
        "totalSecured": 546
      }
    ]
  },
  {
    "rollNumber": "R160720019123",
    "certificateNumber": "180765000456789",
    "traineeName": "SOMA GHOSH",
    "fatherName": "TAPAS GHOSH",
    "motherName": "RUMA GHOSH",
    "dateOfBirth": "14-Feb-1998",
    "admissionDate": "20-Jul-2016",
    "photoUrl": "https://raw.githubusercontent.com/Horsamod/itidata/main/assets/photoid/R160720019123_SOMA_GHOSH.jpg",
    "uidNo": "789123456702",
    "gender": "Female",
    "category": "GENERAL",
    "minority": "None",
    "stateRegNo": "567890",
    "mobileNo": "8901234568",
    "emailId": "soma.ghosh98@gmail.com",
    "highestQualification": "12th",
    "traineeDualMode": "No",
    "applicationFormNo": "2109876",
    "traineeType": "Regular",
    "shift": "Shift 2",
    "unit": "Unit 1",
    "remarks": "High scorer in theory",
    "marksheetAllUrl": "https://raw.githubusercontent.com/Horsamod/itidata/main/assets/files/R160720019123/R160720019123_Marksheet_All.css",
    "certificateUrl": "https://raw.githubusercontent.com/Horsamod/itidata/main/assets/files/R160720019123/R160720019123_NCVTCertificate.pdf",
    "markSheetYear1Url": "https://raw.githubusercontent.com/Horsamod/itidata/main/assets/files/R160720019123/R160720019123_MarkSheet_Year_1.pdf",
    "markSheetYear2Url": "https://raw.githubusercontent.com/Horsamod/itidata/main/assets/files/R160720019123/R160720019123_MarkSheet_Year_2.pdf",
    "itiName": "DARJEELING PRIVATE ITI",
    "itiCode": "PR19000134",
    "itiAddress": "SILIGURI, DARJEELING, WEST BENGAL 734001",
    "district": "DARJEELING",
    "state": "WEST BENGAL",
    "pinCode": "734001",
    "academicSession": "Jul 2016",
    "year": "All",
    "examSystem": "A",
    "examSession": "Jul 2018",
    "resultDate": "29-Aug-2018",
    "tradeName": "Electrician",
    "trainingDuration": "Jul 2016 To Aug 2018",
    "level": "5",
    "certificateType": "1",
    "certificateIssueDate": "29-Aug-2018",
    "certified": true,
    "disable": null,
    "submissionDate": "2025-09-26T17:30:44.123Z",
    "marks": [
      {
        "year": "Year-1",
        "examSession": "Jul 2017",
        "resultDate": "10-Aug-2017",
        "tradeTheoryMax": 100,
        "tradeTheorySecured": 91,
        "employabilitySkillsMax": 50,
        "employabilitySkillsSecured": 47,
        "workshopCalculationMax": 50,
        "workshopCalculationSecured": 48,
        "engineeringDrawingMax": 50,
        "engineeringDrawingSecured": 46,
        "tradePracticalMax": 250,
        "tradePracticalSecured": 225,
        "formativeAssessmentMax": 200,
        "formativeAssessmentSecured": 190,
        "totalMax": 700,
        "totalSecured": 647
      },
      {
        "year": "Year-2",
        "examSession": "Jul 2018",
        "resultDate": "29-Aug-2018",
        "tradeTheoryMax": 100,
        "tradeTheorySecured": 87,
        "employabilitySkillsMax": 0,
        "employabilitySkillsSecured": 0,
        "workshopCalculationMax": 50,
        "workshopCalculationSecured": 47,
        "engineeringDrawingMax": 50,
        "engineeringDrawingSecured": 45,
        "tradePracticalMax": 250,
        "tradePracticalSecured": 210,
        "formativeAssessmentMax": 250,
        "formativeAssessmentSecured": 200,
        "totalMax": 650,
        "totalSecured": 589
      }
    ]
  },
  {
    "rollNumber": "R180920022678",
    "certificateNumber": "200987000789456",
    "traineeName": "MD SAHIL ANSARI",
    "fatherName": "MD YUNUS ANSARI",
    "motherName": "SHAHIDA BEGUM",
    "dateOfBirth": "05-Oct-1999",
    "admissionDate": "22-Sep-2018",
    "photoUrl": "https://raw.githubusercontent.com/Horsamod/itidata/main/assets/photoid/R180920022678_MD_SAHIL_ANSARI.jpg",
    "uidNo": "345678912304",
    "gender": "Male",
    "category": "OBC",
    "minority": "Muslim",
    "stateRegNo": "678234",
    "mobileNo": "9123456780",
    "emailId": "sahil.ansari99@gmail.com",
    "highestQualification": "10th",
    "traineeDualMode": "Yes",
    "applicationFormNo": "1098765",
    "traineeType": "Regular",
    "shift": "Shift 1",
    "unit": "Unit 3",
    "remarks": "Consistent in attendance",
    "marksheetAllUrl": "https://raw.githubusercontent.com/Horsamod/itidata/main/assets/files/R180920022678/R180920022678_Marksheet_All.css",
    "certificateUrl": "https://raw.githubusercontent.com/Horsamod/itidata/main/assets/files/R180920022678/R180920022678_NCVTCertificate.pdf",
    "markSheetYear1Url": "https://raw.githubusercontent.com/Horsamod/itidata/main/assets/files/R180920022678/R180920022678_MarkSheet_Year_1.pdf",
    "markSheetYear2Url": "https://raw.githubusercontent.com/Horsamod/itidata/main/assets/files/R180920022678/R180920022678_MarkSheet_Year_2.pdf",
    "itiName": "JALPAIGURI PRIVATE ITI",
    "itiCode": "PR19000245",
    "itiAddress": "JALPAIGURI ROAD, JALPAIGURI, WEST BENGAL 735101",
    "district": "JALPAIGURI",
    "state": "WEST BENGAL",
    "pinCode": "735101",
    "academicSession": "Sep 2018",
    "year": "All",
    "examSystem": "A",
    "examSession": "Jul 2020",
    "resultDate": "30-Aug-2020",
    "tradeName": "Fitter",
    "trainingDuration": "Sep 2018 To Aug 2020",
    "level": "5",
    "certificateType": "1",
    "certificateIssueDate": "30-Aug-2020",
    "certified": true,
    "disable": null,
    "submissionDate": "2025-09-26T18:40:55.678Z",
    "marks": [
      {
        "year": "Year-1",
        "examSession": "Jul 2019",
        "resultDate": "15-Aug-2019",
        "tradeTheoryMax": 100,
        "tradeTheorySecured": 85,
        "employabilitySkillsMax": 50,
        "employabilitySkillsSecured": 43,
        "workshopCalculationMax": 50,
        "workshopCalculationSecured": 44,
        "engineeringDrawingMax": 50,
        "engineeringDrawingSecured": 42,
        "tradePracticalMax": 250,
        "tradePracticalSecured": 210,
        "formativeAssessmentMax": 200,
        "formativeAssessmentSecured": 175,
        "totalMax": 700,
        "totalSecured": 599
      },
      {
        "year": "Year-2",
        "examSession": "Jul 2020",
        "resultDate": "30-Aug-2020",
        "tradeTheoryMax": 100,
        "tradeTheorySecured": 81,
        "employabilitySkillsMax": 0,
        "employabilitySkillsSecured": 0,
        "workshopCalculationMax": 50,
        "workshopCalculationSecured": 45,
        "engineeringDrawingMax": 50,
        "engineeringDrawingSecured": 43,
        "tradePracticalMax": 250,
        "tradePracticalSecured": 195,
        "formativeAssessmentMax": 250,
        "formativeAssessmentSecured": 185,
        "totalMax": 650,
        "totalSecured": 549
      }
    ]
  },
]